{
	"song": {
		"player1": "popbf",
		"gfVersion": "nobody",
		"notes": [
			{
				"sectionNotes": [],
				"typeOfSection": 0,
				"lengthInSteps": 16,
				"gfSection": false,
				"altAnim": false,
				"mustHitSection": false,
				"changeBPM": false,
				"bpm": 150
			},
			{
				"sectionNotes": [
					[
						1500,
						0,
						281.25
					],
					[
						1875,
						1,
						281.25
					],
					[
						2250,
						2,
						281.25
					],
					[
						2625,
						1,
						656.25
					]
				],
				"typeOfSection": 0,
				"lengthInSteps": 16,
				"gfSection": false,
				"altAnim": false,
				"mustHitSection": false,
				"changeBPM": false,
				"bpm": 150
			},
			{
				"sectionNotes": [
					[
						3375,
						1,
						0
					],
					[
						3562.5,
						0,
						0
					],
					[
						3750,
						1,
						281.25
					],
					[
						4125,
						0,
						281.25
					]
				],
				"typeOfSection": 0,
				"lengthInSteps": 16,
				"gfSection": false,
				"altAnim": false,
				"mustHitSection": true,
				"changeBPM": false,
				"bpm": 150
			},
			{
				"lengthInSteps": 16,
				"typeOfSection": 0,
				"sectionNotes": [
					[
						4500,
						2,
						656.25
					],
					[
						5250,
						3,
						656.25
					]
				],
				"altAnim": false,
				"gfSection": false,
				"bpm": 150,
				"changeBPM": false,
				"mustHitSection": true
			},
			{
				"lengthInSteps": 16,
				"typeOfSection": 0,
				"sectionNotes": [
					[
						6000,
						1,
						656.25
					],
					[
						7125,
						4,
						281.25
					]
				],
				"altAnim": false,
				"gfSection": false,
				"bpm": 160,
				"changeBPM": false,
				"mustHitSection": true
			},
			{
				"lengthInSteps": 16,
				"typeOfSection": 0,
				"sectionNotes": [
					[
						8250,
						0,
						281.25
					],
					[
						7875,
						3,
						281.25
					],
					[
						7500,
						2,
						281.25
					],
					[
						8625,
						2,
						281.25
					]
				],
				"altAnim": false,
				"gfSection": false,
				"bpm": 160,
				"changeBPM": false,
				"mustHitSection": false
			},
			{
				"lengthInSteps": 16,
				"typeOfSection": 0,
				"sectionNotes": [
					[
						9000,
						1,
						656.25
					],
					[
						9750,
						5,
						281.25
					],
					[
						10125,
						7,
						281.25
					]
				],
				"altAnim": false,
				"gfSection": false,
				"bpm": 160,
				"changeBPM": false,
				"mustHitSection": false
			},
			{
				"lengthInSteps": 16,
				"typeOfSection": 0,
				"sectionNotes": [
					[
						11625,
						0,
						281.25
					],
					[
						11250,
						1,
						281.25
					],
					[
						10875,
						2,
						281.25
					],
					[
						10500,
						1,
						281.25
					]
				],
				"altAnim": false,
				"gfSection": false,
				"bpm": 160,
				"changeBPM": false,
				"mustHitSection": true
			},
			{
				"lengthInSteps": 16,
				"typeOfSection": 0,
				"sectionNotes": [
					[
						12000,
						0,
						0
					],
					[
						12281.25,
						0,
						0
					],
					[
						12562.5,
						0,
						0
					],
					[
						12750,
						1,
						0
					],
					[
						12937.5,
						0,
						0
					],
					[
						13125,
						3,
						0
					],
					[
						13312.5,
						1,
						0
					]
				],
				"altAnim": false,
				"gfSection": false,
				"bpm": 160,
				"changeBPM": false,
				"mustHitSection": false
			},
			{
				"lengthInSteps": 16,
				"typeOfSection": 0,
				"sectionNotes": [
					[
						13500,
						2,
						656.25
					],
					[
						14625,
						1,
						0
					],
					[
						14812.5,
						3,
						0
					]
				],
				"altAnim": false,
				"gfSection": false,
				"bpm": 160,
				"changeBPM": false,
				"mustHitSection": false
			},
			{
				"lengthInSteps": 16,
				"typeOfSection": 0,
				"sectionNotes": [
					[
						15375,
						0,
						1031.25
					],
					[
						15000,
						2,
						281.25
					]
				],
				"altAnim": false,
				"gfSection": false,
				"bpm": 160,
				"changeBPM": false,
				"mustHitSection": false
			},
			{
				"lengthInSteps": 16,
				"typeOfSection": 0,
				"sectionNotes": [
					[
						16875,
						1,
						281.25
					],
					[
						16500,
						3,
						656.25
					],
					[
						17250,
						2,
						281.25
					],
					[
						17625,
						0,
						281.25
					]
				],
				"altAnim": false,
				"gfSection": false,
				"bpm": 160,
				"changeBPM": false,
				"mustHitSection": false
			},
			{
				"lengthInSteps": 16,
				"typeOfSection": 0,
				"sectionNotes": [
					[
						18000,
						1,
						0
					],
					[
						18281.25,
						1,
						0
					],
					[
						18562.5,
						1,
						0
					],
					[
						18750,
						0,
						0
					],
					[
						18937.5,
						1,
						0
					],
					[
						19125,
						0,
						0
					],
					[
						19312.5,
						2,
						0
					]
				],
				"altAnim": false,
				"gfSection": false,
				"bpm": 160,
				"changeBPM": false,
				"mustHitSection": true
			},
			{
				"lengthInSteps": 16,
				"typeOfSection": 0,
				"sectionNotes": [
					[
						19500,
						1,
						656.25
					],
					[
						20812.5,
						1,
						0
					],
					[
						20625,
						0,
						0
					]
				],
				"altAnim": false,
				"gfSection": false,
				"bpm": 160,
				"changeBPM": false,
				"mustHitSection": true
			},
			{
				"lengthInSteps": 16,
				"typeOfSection": 0,
				"sectionNotes": [
					[
						21000,
						2,
						281.25
					],
					[
						21375,
						1,
						843.75
					]
				],
				"altAnim": false,
				"gfSection": false,
				"bpm": 160,
				"changeBPM": false,
				"mustHitSection": true
			},
			{
				"lengthInSteps": 16,
				"typeOfSection": 0,
				"sectionNotes": [
					[
						22500,
						0,
						656.25
					],
					[
						22875,
						2,
						281.25
					],
					[
						23250,
						1,
						281.25
					],
					[
						23625,
						0,
						281.25
					]
				],
				"altAnim": false,
				"gfSection": false,
				"bpm": 160,
				"changeBPM": false,
				"mustHitSection": true
			},
			{
				"lengthInSteps": 16,
				"typeOfSection": 0,
				"sectionNotes": [
					[
						24375,
						2,
						0
					],
					[
						24562.5,
						2,
						0
					],
					[
						24750,
						0,
						0
					],
					[
						24937.5,
						3,
						0
					],
					[
						25125,
						0,
						0
					],
					[
						25312.5,
						2,
						0
					]
				],
				"altAnim": false,
				"gfSection": false,
				"bpm": 160,
				"changeBPM": false,
				"mustHitSection": false
			},
			{
				"lengthInSteps": 16,
				"typeOfSection": 0,
				"sectionNotes": [
					[
						25500,
						1,
						0
					],
					[
						25875,
						2,
						0
					],
					[
						26250,
						1,
						0
					],
					[
						26437.5,
						3,
						0
					],
					[
						26625,
						2,
						0
					],
					[
						26812.5,
						3,
						0
					]
				],
				"altAnim": false,
				"gfSection": false,
				"bpm": 160,
				"changeBPM": false,
				"mustHitSection": false
			},
			{
				"lengthInSteps": 16,
				"typeOfSection": 0,
				"sectionNotes": [
					[
						27375,
						2,
						0
					],
					[
						27562.5,
						2,
						0
					],
					[
						27750,
						1,
						0
					],
					[
						27937.5,
						3,
						0
					],
					[
						28125,
						0,
						0
					],
					[
						28312.5,
						3,
						0
					],
					[
						27000,
						0,
						281.25
					]
				],
				"altAnim": false,
				"gfSection": false,
				"bpm": 160,
				"changeBPM": false,
				"mustHitSection": false
			},
			{
				"lengthInSteps": 16,
				"typeOfSection": 0,
				"sectionNotes": [
					[
						28500,
						0,
						0
					],
					[
						28875,
						2,
						0
					],
					[
						29250,
						0,
						0
					],
					[
						29625,
						1,
						0
					],
					[
						29812.5,
						0,
						0
					],
					[
						29437.5,
						2,
						0
					]
				],
				"altAnim": false,
				"gfSection": false,
				"bpm": 160,
				"changeBPM": false,
				"mustHitSection": false
			},
			{
				"lengthInSteps": 16,
				"typeOfSection": 0,
				"sectionNotes": [
					[
						30375,
						1,
						0
					],
					[
						30562.5,
						1,
						0
					],
					[
						30750,
						3,
						0
					],
					[
						30937.5,
						0,
						0
					],
					[
						31125,
						3,
						0
					],
					[
						31312.5,
						1,
						0
					]
				],
				"altAnim": false,
				"gfSection": false,
				"bpm": 160,
				"changeBPM": false,
				"mustHitSection": true
			},
			{
				"lengthInSteps": 16,
				"typeOfSection": 0,
				"sectionNotes": [
					[
						31500,
						2,
						0
					],
					[
						31875,
						1,
						0
					],
					[
						32250,
						2,
						0
					],
					[
						32437.5,
						0,
						0
					],
					[
						32625,
						3,
						0
					],
					[
						32812.5,
						0,
						0
					]
				],
				"altAnim": false,
				"gfSection": false,
				"bpm": 160,
				"changeBPM": false,
				"mustHitSection": true
			},
			{
				"lengthInSteps": 16,
				"typeOfSection": 0,
				"sectionNotes": [
					[
						33000,
						1,
						0
					],
					[
						33187.5,
						1,
						0
					],
					[
						33375,
						0,
						0
					],
					[
						33562.5,
						0,
						0
					],
					[
						33750,
						3,
						0
					],
					[
						34125,
						1,
						0
					],
					[
						34312.5,
						0,
						0
					],
					[
						33750,
						2,
						93.75
					],
					[
						33937.5,
						3,
						0
					]
				],
				"altAnim": false,
				"gfSection": false,
				"bpm": 160,
				"changeBPM": false,
				"mustHitSection": true
			},
			{
				"lengthInSteps": 16,
				"typeOfSection": 0,
				"sectionNotes": [
					[
						34500,
						1,
						93.75
					],
					[
						34875,
						3,
						93.75
					],
					[
						35250,
						1,
						93.75
					],
					[
						35437.5,
						3,
						93.75
					],
					[
						35625,
						0,
						93.75
					],
					[
						35812.5,
						1,
						93.75
					]
				],
				"altAnim": false,
				"gfSection": false,
				"bpm": 160,
				"changeBPM": false,
				"mustHitSection": true
			},
			{
				"lengthInSteps": 16,
				"typeOfSection": 0,
				"sectionNotes": [
					[
						36000,
						7,
						843.75
					],
					[
						36187.5,
						0,
						0
					],
					[
						36375,
						2,
						0
					],
					[
						36562.5,
						3,
						0
					],
					[
						36750,
						2,
						0
					],
					[
						36937.5,
						3,
						0
					],
					[
						37125,
						0,
						0
					],
					[
						37312.5,
						2,
						0
					]
				],
				"altAnim": false,
				"gfSection": false,
				"bpm": 160,
				"changeBPM": false,
				"mustHitSection": false
			},
			{
				"lengthInSteps": 16,
				"typeOfSection": 0,
				"sectionNotes": [
					[
						37500,
						0,
						0
					],
					[
						37875,
						1,
						0
					],
					[
						38250,
						0,
						0
					],
					[
						38625,
						3,
						0
					]
				],
				"altAnim": false,
				"gfSection": false,
				"bpm": 160,
				"changeBPM": false,
				"mustHitSection": false
			},
			{
				"lengthInSteps": 16,
				"typeOfSection": 0,
				"sectionNotes": [
					[
						40125,
						1,
						0
					],
					[
						40312.5,
						3,
						0
					],
					[
						39000,
						2,
						656.25
					],
					[
						39000,
						3,
						656.25
					]
				],
				"altAnim": false,
				"gfSection": false,
				"bpm": 160,
				"changeBPM": false,
				"mustHitSection": false
			},
			{
				"lengthInSteps": 16,
				"typeOfSection": 0,
				"sectionNotes": [
					[
						40500,
						0,
						656.25
					],
					[
						41250,
						2,
						281.25
					],
					[
						41625,
						1,
						281.25
					]
				],
				"altAnim": false,
				"gfSection": false,
				"bpm": 160,
				"changeBPM": false,
				"mustHitSection": false
			},
			{
				"lengthInSteps": 16,
				"typeOfSection": 0,
				"sectionNotes": [
					[
						42000,
						4,
						1406.25
					],
					[
						42187.5,
						0,
						0
					],
					[
						42375,
						2,
						0
					],
					[
						42562.5,
						1,
						0
					],
					[
						42750,
						0,
						0
					],
					[
						42937.5,
						1,
						0
					],
					[
						43125,
						2,
						0
					],
					[
						43312.5,
						1,
						0
					]
				],
				"altAnim": false,
				"gfSection": false,
				"bpm": 160,
				"changeBPM": false,
				"mustHitSection": true
			},
			{
				"lengthInSteps": 16,
				"typeOfSection": 0,
				"sectionNotes": [
					[
						43500,
						0,
						93.75
					],
					[
						43875,
						2,
						93.75
					],
					[
						44250,
						0,
						93.75
					],
					[
						44625,
						1,
						93.75
					]
				],
				"altAnim": false,
				"gfSection": false,
				"bpm": 160,
				"changeBPM": false,
				"mustHitSection": true
			},
			{
				"lengthInSteps": 16,
				"typeOfSection": 0,
				"sectionNotes": [
					[
						45375,
						1,
						0
					],
					[
						45562.5,
						0,
						0
					],
					[
						46125,
						3,
						0
					],
					[
						46312.5,
						0,
						0
					],
					[
						45000,
						2,
						281.25
					],
					[
						45750,
						2,
						281.25
					]
				],
				"altAnim": false,
				"gfSection": false,
				"bpm": 160,
				"changeBPM": false,
				"mustHitSection": true
			},
			{
				"lengthInSteps": 16,
				"typeOfSection": 0,
				"sectionNotes": [
					[
						47062.5,
						1,
						0
					],
					[
						46500,
						3,
						281.25
					],
					[
						46875,
						2,
						0
					],
					[
						47250,
						2,
						281.25
					],
					[
						47625,
						0,
						281.25
					]
				],
				"altAnim": false,
				"gfSection": false,
				"bpm": 160,
				"changeBPM": false,
				"mustHitSection": true
			},
			{
				"lengthInSteps": 16,
				"typeOfSection": 0,
				"sectionNotes": [
					[
						48187.5,
						0,
						0
					],
					[
						48375,
						2,
						0
					],
					[
						48562.5,
						3,
						0
					],
					[
						48750,
						2,
						0
					],
					[
						48937.5,
						3,
						0
					],
					[
						49125,
						0,
						0
					],
					[
						49312.5,
						2,
						0
					],
					[
						48000,
						5,
						750
					]
				],
				"altAnim": false,
				"gfSection": false,
				"bpm": 160,
				"changeBPM": false,
				"mustHitSection": false
			},
			{
				"lengthInSteps": 16,
				"typeOfSection": 0,
				"sectionNotes": [
					[
						49875,
						1,
						0
					],
					[
						50250,
						0,
						0
					],
					[
						49500,
						3,
						0
					],
					[
						50625,
						1,
						0
					]
				],
				"altAnim": false,
				"gfSection": false,
				"bpm": 160,
				"changeBPM": false,
				"mustHitSection": false
			},
			{
				"lengthInSteps": 16,
				"typeOfSection": 0,
				"sectionNotes": [
					[
						51000,
						2,
						281.25
					],
					[
						51375,
						3,
						281.25
					],
					[
						51937.5,
						1,
						0
					],
					[
						52125,
						0,
						0
					],
					[
						52312.5,
						1,
						0
					]
				],
				"altAnim": false,
				"gfSection": false,
				"bpm": 160,
				"changeBPM": false,
				"mustHitSection": false
			},
			{
				"lengthInSteps": 16,
				"typeOfSection": 0,
				"sectionNotes": [
					[
						53437.5,
						1,
						0
					],
					[
						53625,
						3,
						0
					],
					[
						53812.5,
						2,
						0
					],
					[
						52875,
						0,
						281.25
					],
					[
						52500,
						1,
						281.25
					]
				],
				"altAnim": false,
				"gfSection": false,
				"bpm": 160,
				"changeBPM": false,
				"mustHitSection": false
			},
			{
				"lengthInSteps": 16,
				"typeOfSection": 0,
				"sectionNotes": [
					[
						54000,
						4,
						1406.25
					],
					[
						54000,
						4,
						1406.25
					],
					[
						54187.5,
						0,
						0
					],
					[
						54375,
						2,
						0
					],
					[
						54562.5,
						1,
						0
					],
					[
						54750,
						0,
						0
					],
					[
						54937.5,
						1,
						0
					],
					[
						55125,
						2,
						0
					],
					[
						55312.5,
						1,
						0
					]
				],
				"altAnim": false,
				"gfSection": false,
				"bpm": 160,
				"changeBPM": false,
				"mustHitSection": true
			},
			{
				"lengthInSteps": 16,
				"typeOfSection": 0,
				"sectionNotes": [
					[
						55500,
						0,
						93.75
					],
					[
						56250,
						0,
						93.75
					],
					[
						56625,
						1,
						93.75
					],
					[
						55875,
						1,
						93.75
					]
				],
				"altAnim": false,
				"gfSection": false,
				"bpm": 160,
				"changeBPM": false,
				"mustHitSection": true
			},
			{
				"lengthInSteps": 16,
				"typeOfSection": 0,
				"sectionNotes": [
					[
						57000,
						2,
						281.25
					],
					[
						57937.5,
						1,
						0
					],
					[
						58125,
						0,
						0
					],
					[
						58312.5,
						1,
						0
					],
					[
						57375,
						1,
						281.25
					]
				],
				"altAnim": false,
				"gfSection": false,
				"bpm": 160,
				"changeBPM": false,
				"mustHitSection": true
			},
			{
				"lengthInSteps": 16,
				"typeOfSection": 0,
				"sectionNotes": [
					[
						59250,
						1,
						0
					],
					[
						59437.5,
						1,
						0
					],
					[
						59625,
						1,
						0
					],
					[
						59718.75,
						0,
						0
					],
					[
						59812.5,
						1,
						0
					],
					[
						59906.25,
						0,
						0
					],
					[
						58500,
						3,
						281.25
					],
					[
						58875,
						1,
						93.75
					]
				],
				"altAnim": false,
				"gfSection": false,
				"bpm": 160,
				"changeBPM": false,
				"mustHitSection": true
			},
			{
				"lengthInSteps": 16,
				"typeOfSection": 0,
				"sectionNotes": [
					[
						60375,
						0,
						0
					],
					[
						60937.5,
						3,
						0
					],
					[
						61031.25,
						2,
						0
					],
					[
						60187.5,
						3,
						0
					],
					[
						60281.25,
						2,
						0
					],
					[
						60468.75,
						2,
						0
					],
					[
						60562.5,
						3,
						0
					],
					[
						60656.25,
						2,
						0
					],
					[
						60750,
						1,
						93.75
					],
					[
						61125,
						3,
						93.75
					],
					[
						61312.5,
						1,
						93.75
					]
				],
				"altAnim": false,
				"gfSection": false,
				"bpm": 160,
				"changeBPM": false,
				"mustHitSection": false
			},
			{
				"lengthInSteps": 16,
				"typeOfSection": 0,
				"sectionNotes": [
					[
						61687.5,
						3,
						0
					],
					[
						61781.25,
						2,
						0
					],
					[
						61875,
						0,
						0
					],
					[
						61968.75,
						2,
						0
					],
					[
						62062.5,
						3,
						0
					],
					[
						62156.25,
						2,
						0
					],
					[
						62437.5,
						0,
						0
					],
					[
						62531.25,
						2,
						0
					],
					[
						62250,
						1,
						93.75
					],
					[
						62625,
						3,
						93.75
					],
					[
						62812.5,
						0,
						93.75
					]
				],
				"altAnim": false,
				"gfSection": false,
				"bpm": 160,
				"changeBPM": false,
				"mustHitSection": false
			},
			{
				"lengthInSteps": 16,
				"typeOfSection": 0,
				"sectionNotes": [
					[
						63187.5,
						1,
						0
					],
					[
						63281.25,
						3,
						0
					],
					[
						63375,
						1,
						0
					],
					[
						63468.75,
						0,
						0
					],
					[
						63562.5,
						1,
						0
					],
					[
						63656.25,
						3,
						0
					],
					[
						63937.5,
						1,
						0
					],
					[
						64031.25,
						0,
						0
					],
					[
						64125,
						1,
						93.75
					],
					[
						63750,
						2,
						93.75
					],
					[
						64312.5,
						3,
						93.75
					]
				],
				"altAnim": false,
				"gfSection": false,
				"bpm": 160,
				"changeBPM": false,
				"mustHitSection": false
			},
			{
				"lengthInSteps": 16,
				"typeOfSection": 0,
				"sectionNotes": [
					[
						64781.25,
						3,
						0
					],
					[
						64687.5,
						1,
						0
					],
					[
						64875,
						1,
						0
					],
					[
						64968.75,
						0,
						0
					],
					[
						65062.5,
						1,
						0
					],
					[
						65156.25,
						3,
						0
					],
					[
						65250,
						1,
						656.25
					]
				],
				"altAnim": false,
				"gfSection": false,
				"bpm": 160,
				"changeBPM": false,
				"mustHitSection": false
			},
			{
				"lengthInSteps": 16,
				"typeOfSection": 0,
				"sectionNotes": [
					[
						66375,
						3,
						0
					],
					[
						66937.5,
						0,
						0
					],
					[
						67031.25,
						1,
						0
					],
					[
						66187.5,
						0,
						0
					],
					[
						66281.25,
						1,
						0
					],
					[
						66468.75,
						1,
						0
					],
					[
						66562.5,
						0,
						0
					],
					[
						66656.25,
						1,
						0
					],
					[
						66750,
						2,
						93.75
					],
					[
						67125,
						0,
						93.75
					],
					[
						67312.5,
						2,
						93.75
					]
				],
				"altAnim": false,
				"gfSection": false,
				"bpm": 160,
				"changeBPM": false,
				"mustHitSection": true
			},
			{
				"lengthInSteps": 16,
				"typeOfSection": 0,
				"sectionNotes": [
					[
						67687.5,
						0,
						0
					],
					[
						67781.25,
						1,
						0
					],
					[
						67875,
						3,
						0
					],
					[
						67968.75,
						1,
						0
					],
					[
						68062.5,
						0,
						0
					],
					[
						68156.25,
						1,
						0
					],
					[
						68437.5,
						3,
						0
					],
					[
						68531.25,
						1,
						0
					],
					[
						68250,
						2,
						93.75
					],
					[
						68625,
						0,
						93.75
					],
					[
						68812.5,
						1,
						93.75
					]
				],
				"altAnim": false,
				"gfSection": false,
				"bpm": 160,
				"changeBPM": false,
				"mustHitSection": true
			},
			{
				"lengthInSteps": 16,
				"typeOfSection": 0,
				"sectionNotes": [
					[
						69187.5,
						2,
						0
					],
					[
						69281.25,
						0,
						0
					],
					[
						69375,
						2,
						0
					],
					[
						69468.75,
						3,
						0
					],
					[
						69562.5,
						2,
						0
					],
					[
						69656.25,
						0,
						0
					],
					[
						69937.5,
						2,
						0
					],
					[
						70031.25,
						3,
						0
					],
					[
						70125,
						2,
						93.75
					],
					[
						69750,
						1,
						93.75
					],
					[
						70312.5,
						3,
						93.75
					]
				],
				"altAnim": false,
				"gfSection": false,
				"bpm": 160,
				"changeBPM": false,
				"mustHitSection": true
			},
			{
				"lengthInSteps": 16,
				"typeOfSection": 0,
				"sectionNotes": [
					[
						70781.25,
						0,
						0
					],
					[
						70687.5,
						2,
						0
					],
					[
						70968.75,
						3,
						0
					],
					[
						71062.5,
						2,
						0
					],
					[
						71156.25,
						0,
						0
					],
					[
						70875,
						1,
						0
					],
					[
						71812.5,
						2,
						93.75
					],
					[
						71625,
						0,
						93.75
					],
					[
						71437.5,
						3,
						93.75
					],
					[
						71250,
						2,
						93.75
					]
				],
				"altAnim": false,
				"gfSection": false,
				"bpm": 160,
				"changeBPM": false,
				"mustHitSection": true
			},
			{
				"lengthInSteps": 16,
				"typeOfSection": 0,
				"sectionNotes": [
					[
						72000,
						0,
						0
					],
					[
						72046.875,
						1,
						0
					],
					[
						72093.75,
						2,
						0
					],
					[
						72140.625,
						3,
						0
					],
					[
						72187.5,
						0,
						0
					],
					[
						72234.375,
						1,
						0
					],
					[
						72281.25,
						2,
						0
					],
					[
						72656.25,
						3,
						0
					],
					[
						72750,
						0,
						0
					],
					[
						72937.5,
						1,
						0
					],
					[
						73125,
						3,
						0
					],
					[
						73312.5,
						1,
						0
					],
					[
						72375,
						3,
						0
					],
					[
						72515.625,
						2,
						0
					]
				],
				"altAnim": false,
				"gfSection": false,
				"bpm": 160,
				"changeBPM": false,
				"mustHitSection": false
			},
			{
				"lengthInSteps": 16,
				"typeOfSection": 0,
				"sectionNotes": [
					[
						73500,
						0,
						0
					],
					[
						73687.5,
						1,
						0
					],
					[
						73875,
						3,
						0
					],
					[
						74062.5,
						1,
						0
					],
					[
						74250,
						2,
						0
					],
					[
						74437.5,
						1,
						0
					],
					[
						74625,
						3,
						0
					],
					[
						74812.5,
						2,
						0
					]
				],
				"altAnim": false,
				"gfSection": false,
				"bpm": 160,
				"changeBPM": false,
				"mustHitSection": false
			},
			{
				"lengthInSteps": 16,
				"typeOfSection": 0,
				"sectionNotes": [
					[
						75000,
						0,
						0
					],
					[
						75046.875,
						1,
						0
					],
					[
						75093.75,
						2,
						0
					],
					[
						75140.625,
						3,
						0
					],
					[
						75187.5,
						0,
						0
					],
					[
						75234.375,
						1,
						0
					],
					[
						75281.25,
						2,
						0
					],
					[
						75328.125,
						3,
						0
					],
					[
						75656.25,
						3,
						0
					],
					[
						75750,
						1,
						0
					],
					[
						75937.5,
						2,
						0
					],
					[
						76125,
						1,
						0
					],
					[
						76312.5,
						3,
						0
					],
					[
						75515.625,
						2,
						0
					],
					[
						75375,
						0,
						0
					]
				],
				"altAnim": false,
				"gfSection": false,
				"bpm": 160,
				"changeBPM": false,
				"mustHitSection": false
			},
			{
				"lengthInSteps": 16,
				"typeOfSection": 0,
				"sectionNotes": [
					[
						76500,
						1,
						0
					],
					[
						76687.5,
						2,
						0
					],
					[
						76875,
						0,
						0
					],
					[
						77062.5,
						3,
						0
					],
					[
						77250,
						1,
						0
					],
					[
						77437.5,
						3,
						0
					],
					[
						77625,
						2,
						0
					],
					[
						77812.5,
						0,
						0
					]
				],
				"altAnim": false,
				"gfSection": false,
				"bpm": 160,
				"changeBPM": false,
				"mustHitSection": false
			},
			{
				"lengthInSteps": 16,
				"typeOfSection": 0,
				"sectionNotes": [
					[
						78000,
						3,
						0
					],
					[
						78046.875,
						2,
						0
					],
					[
						78093.75,
						1,
						0
					],
					[
						78140.625,
						0,
						0
					],
					[
						78187.5,
						3,
						0
					],
					[
						78234.375,
						2,
						0
					],
					[
						78281.25,
						1,
						0
					],
					[
						78937.5,
						2,
						0
					],
					[
						79125,
						0,
						0
					],
					[
						79312.5,
						2,
						0
					],
					[
						78656.25,
						2,
						0
					],
					[
						78515.625,
						3,
						0
					],
					[
						78750,
						1,
						0
					],
					[
						78375,
						0,
						0
					]
				],
				"altAnim": false,
				"gfSection": false,
				"bpm": 160,
				"changeBPM": false,
				"mustHitSection": true
			},
			{
				"lengthInSteps": 16,
				"typeOfSection": 0,
				"sectionNotes": [
					[
						79500,
						0,
						0
					],
					[
						79687.5,
						1,
						0
					],
					[
						80062.5,
						1,
						0
					],
					[
						80437.5,
						1,
						0
					],
					[
						80625,
						0,
						0
					],
					[
						80812.5,
						2,
						0
					],
					[
						79875,
						2,
						0
					],
					[
						80250,
						0,
						0
					]
				],
				"altAnim": false,
				"gfSection": false,
				"bpm": 160,
				"changeBPM": false,
				"mustHitSection": true
			},
			{
				"lengthInSteps": 16,
				"typeOfSection": 0,
				"sectionNotes": [
					[
						81000,
						3,
						0
					],
					[
						81046.875,
						2,
						0
					],
					[
						81093.75,
						1,
						0
					],
					[
						81140.625,
						0,
						0
					],
					[
						81187.5,
						3,
						0
					],
					[
						81234.375,
						2,
						0
					],
					[
						81281.25,
						1,
						0
					],
					[
						81328.125,
						0,
						0
					],
					[
						81375,
						3,
						0
					],
					[
						81515.625,
						1,
						0
					],
					[
						82312.5,
						3,
						0
					],
					[
						81656.25,
						3,
						0
					],
					[
						81750,
						2,
						0
					],
					[
						81937.5,
						3,
						0
					],
					[
						82125,
						1,
						0
					]
				],
				"altAnim": false,
				"gfSection": false,
				"bpm": 160,
				"changeBPM": false,
				"mustHitSection": true
			},
			{
				"lengthInSteps": 16,
				"typeOfSection": 0,
				"sectionNotes": [
					[
						83062.5,
						3,
						0
					],
					[
						83250,
						0,
						0
					],
					[
						82500,
						0,
						0
					],
					[
						82687.5,
						3,
						0
					],
					[
						82875,
						1,
						0
					],
					[
						83437.5,
						3,
						0
					],
					[
						83625,
						2,
						0
					],
					[
						83812.5,
						1,
						0
					]
				],
				"altAnim": false,
				"gfSection": false,
				"bpm": 160,
				"changeBPM": false,
				"mustHitSection": true
			},
			{
				"lengthInSteps": 16,
				"typeOfSection": 0,
				"sectionNotes": [
					[
						84187.5,
						3,
						0
					],
					[
						84375,
						0,
						0
					],
					[
						84468.75,
						2,
						0
					],
					[
						84562.5,
						3,
						0
					],
					[
						84656.25,
						2,
						0
					],
					[
						84937.5,
						3,
						0
					],
					[
						85031.25,
						2,
						0
					],
					[
						84750,
						1,
						93.75
					],
					[
						85125,
						3,
						93.75
					],
					[
						85312.5,
						2,
						93.75
					],
					[
						84281.25,
						2,
						0
					]
				],
				"altAnim": false,
				"gfSection": false,
				"bpm": 160,
				"changeBPM": false,
				"mustHitSection": false
			},
			{
				"lengthInSteps": 16,
				"typeOfSection": 0,
				"sectionNotes": [
					[
						85781.25,
						2,
						0
					],
					[
						85875,
						0,
						0
					],
					[
						85968.75,
						2,
						0
					],
					[
						86156.25,
						2,
						0
					],
					[
						86437.5,
						0,
						0
					],
					[
						86531.25,
						2,
						0
					],
					[
						86250,
						1,
						93.75
					],
					[
						86625,
						3,
						93.75
					],
					[
						86812.5,
						0,
						93.75
					],
					[
						85687.5,
						1,
						0
					],
					[
						86062.5,
						3,
						0
					]
				],
				"altAnim": false,
				"gfSection": false,
				"bpm": 160,
				"changeBPM": false,
				"mustHitSection": false
			},
			{
				"lengthInSteps": 16,
				"typeOfSection": 0,
				"sectionNotes": [
					[
						87187.5,
						0,
						0
					],
					[
						87281.25,
						2,
						0
					],
					[
						87562.5,
						0,
						0
					],
					[
						87000,
						2,
						93.75
					],
					[
						87375,
						3,
						93.75
					],
					[
						87750,
						1,
						93.75
					],
					[
						87937.5,
						2,
						93.75
					],
					[
						88125,
						3,
						93.75
					],
					[
						88312.5,
						1,
						93.75
					],
					[
						87656.25,
						2,
						0
					]
				],
				"altAnim": false,
				"gfSection": false,
				"bpm": 160,
				"changeBPM": false,
				"mustHitSection": false
			},
			{
				"lengthInSteps": 16,
				"typeOfSection": 0,
				"sectionNotes": [
					[
						88687.5,
						0,
						0
					],
					[
						88781.25,
						2,
						0
					],
					[
						89062.5,
						0,
						0
					],
					[
						89156.25,
						2,
						0
					],
					[
						89250,
						1,
						93.75
					],
					[
						89437.5,
						3,
						93.75
					],
					[
						89812.5,
						2,
						93.75
					],
					[
						88875,
						3,
						93.75
					],
					[
						88500,
						2,
						93.75
					],
					[
						89625,
						0,
						93.75
					]
				],
				"altAnim": false,
				"gfSection": false,
				"bpm": 160,
				"changeBPM": false,
				"mustHitSection": false
			},
			{
				"lengthInSteps": 16,
				"typeOfSection": 0,
				"sectionNotes": [
					[
						90187.5,
						0,
						0
					],
					[
						90281.25,
						1,
						0
					],
					[
						90375,
						3,
						0
					],
					[
						90468.75,
						1,
						0
					],
					[
						90562.5,
						0,
						0
					],
					[
						90656.25,
						1,
						0
					],
					[
						90937.5,
						0,
						0
					],
					[
						91031.25,
						1,
						0
					],
					[
						90750,
						2,
						93.75
					],
					[
						91125,
						0,
						93.75
					],
					[
						91312.5,
						2,
						93.75
					]
				],
				"altAnim": false,
				"gfSection": false,
				"bpm": 160,
				"changeBPM": false,
				"mustHitSection": true
			},
			{
				"lengthInSteps": 16,
				"typeOfSection": 0,
				"sectionNotes": [
					[
						91687.5,
						0,
						0
					],
					[
						91875,
						3,
						0
					],
					[
						92062.5,
						0,
						0
					],
					[
						92437.5,
						3,
						0
					],
					[
						92531.25,
						1,
						0
					],
					[
						92625,
						0,
						93.75
					],
					[
						92250,
						1,
						93.75
					],
					[
						92156.25,
						2,
						0
					],
					[
						91968.75,
						2,
						0
					],
					[
						91781.25,
						2,
						0
					],
					[
						92812.5,
						1,
						93.75
					]
				],
				"altAnim": false,
				"gfSection": false,
				"bpm": 160,
				"changeBPM": false,
				"mustHitSection": true
			},
			{
				"lengthInSteps": 16,
				"typeOfSection": 0,
				"sectionNotes": [
					[
						93187.5,
						0,
						0
					],
					[
						93281.25,
						2,
						0
					],
					[
						93562.5,
						0,
						0
					],
					[
						93656.25,
						2,
						0
					],
					[
						93000,
						2,
						93.75
					],
					[
						93375,
						3,
						93.75
					],
					[
						93750,
						1,
						93.75
					],
					[
						93937.5,
						2,
						93.75
					],
					[
						94125,
						3,
						93.75
					],
					[
						94312.5,
						1,
						93.75
					]
				],
				"altAnim": false,
				"gfSection": false,
				"bpm": 160,
				"changeBPM": false,
				"mustHitSection": true
			},
			{
				"lengthInSteps": 16,
				"typeOfSection": 0,
				"sectionNotes": [
					[
						94687.5,
						0,
						0
					],
					[
						94781.25,
						2,
						0
					],
					[
						95062.5,
						0,
						0
					],
					[
						94875,
						3,
						93.75
					],
					[
						94500,
						2,
						93.75
					],
					[
						95156.25,
						1,
						0
					],
					[
						95343.75,
						3,
						93.75
					],
					[
						95625,
						1,
						0
					],
					[
						95718.75,
						0,
						0
					],
					[
						95859.375,
						1,
						0
					]
				],
				"altAnim": false,
				"gfSection": false,
				"bpm": 160,
				"changeBPM": false,
				"mustHitSection": true
			},
			{
				"lengthInSteps": 16,
				"typeOfSection": 0,
				"sectionNotes": [
					[
						96166.6666666667,
						3,
						0
					],
					[
						96250,
						2,
						0
					],
					[
						96333.3333333333,
						3,
						0
					],
					[
						96500,
						3,
						0
					],
					[
						96416.6666666667,
						1,
						0
					],
					[
						96583.3333333333,
						2,
						0
					],
					[
						96833.3333333333,
						1,
						0
					],
					[
						96916.6666666667,
						0,
						0
					],
					[
						96666.6666666667,
						3,
						83.3333333333333
					],
					[
						97000,
						1,
						83.3333333333333
					],
					[
						97166.6666666667,
						3,
						83.3333333333333
					]
				],
				"altAnim": false,
				"gfSection": false,
				"bpm": 180,
				"changeBPM": true,
				"mustHitSection": false
			},
			{
				"lengthInSteps": 16,
				"typeOfSection": 0,
				"sectionNotes": [
					[
						97500,
						3,
						0
					],
					[
						97583.3333333333,
						2,
						0
					],
					[
						97666.6666666667,
						0,
						0
					],
					[
						97750,
						2,
						0
					],
					[
						97833.3333333333,
						1,
						0
					],
					[
						97916.6666666667,
						3,
						0
					],
					[
						98250,
						0,
						0
					],
					[
						98000,
						0,
						83.3333333333333
					],
					[
						98166.6666666667,
						2,
						0
					],
					[
						98333.3333333333,
						2,
						83.3333333333333
					],
					[
						98500,
						0,
						83.3333333333333
					]
				],
				"altAnim": false,
				"gfSection": false,
				"bpm": 160,
				"changeBPM": false,
				"mustHitSection": false
			},
			{
				"lengthInSteps": 16,
				"typeOfSection": 0,
				"sectionNotes": [
					[
						98666.6666666667,
						1,
						0
					],
					[
						98833.3333333333,
						2,
						0
					],
					[
						98916.6666666667,
						3,
						0
					],
					[
						99166.6666666667,
						2,
						0
					],
					[
						99250,
						3,
						0
					],
					[
						99000,
						0,
						83.3333333333333
					],
					[
						99333.3333333333,
						2,
						83.3333333333333
					],
					[
						99500,
						3,
						83.3333333333333
					],
					[
						99666.6666666667,
						2,
						83.3333333333333
					],
					[
						99833.3333333333,
						0,
						83.3333333333333
					]
				],
				"altAnim": false,
				"gfSection": false,
				"bpm": 160,
				"changeBPM": false,
				"mustHitSection": false
			},
			{
				"lengthInSteps": 16,
				"typeOfSection": 0,
				"sectionNotes": [
					[
						100250,
						2,
						0
					],
					[
						100500,
						0,
						0
					],
					[
						100583.333333333,
						2,
						0
					],
					[
						100666.666666667,
						0,
						83.3333333333333
					],
					[
						100833.333333333,
						1,
						83.3333333333333
					],
					[
						101000,
						3,
						83.3333333333333
					],
					[
						101166.666666667,
						1,
						83.3333333333333
					],
					[
						100000,
						2,
						83.3333333333333
					],
					[
						100166.666666667,
						0,
						0
					],
					[
						100333.333333333,
						3,
						83.3333333333333
					]
				],
				"altAnim": false,
				"gfSection": false,
				"bpm": 160,
				"changeBPM": false,
				"mustHitSection": false
			},
			{
				"lengthInSteps": 16,
				"typeOfSection": 0,
				"sectionNotes": [
					[
						101666.666666667,
						3,
						0
					],
					[
						101500,
						0,
						0
					],
					[
						101583.333333333,
						1,
						0
					],
					[
						101750,
						1,
						0
					],
					[
						101833.333333333,
						0,
						0
					],
					[
						101916.666666667,
						1,
						0
					],
					[
						102000,
						0,
						0
					],
					[
						102166.666666667,
						2,
						0
					],
					[
						102250,
						1,
						0
					],
					[
						102333.333333333,
						0,
						166.666666666667
					]
				],
				"altAnim": false,
				"gfSection": false,
				"bpm": 160,
				"changeBPM": false,
				"mustHitSection": true
			},
			{
				"lengthInSteps": 16,
				"typeOfSection": 0,
				"sectionNotes": [
					[
						102666.666666667,
						1,
						0
					],
					[
						102833.333333333,
						0,
						0
					],
					[
						102916.666666667,
						1,
						0
					],
					[
						103000,
						3,
						0
					],
					[
						103083.333333333,
						1,
						0
					],
					[
						103166.666666667,
						0,
						0
					],
					[
						103250,
						1,
						0
					],
					[
						103500,
						3,
						0
					],
					[
						103333.333333333,
						0,
						83.3333333333333
					],
					[
						103583.333333333,
						1,
						0
					],
					[
						103666.666666667,
						0,
						83.3333333333333
					],
					[
						103833.333333333,
						2,
						83.3333333333333
					]
				],
				"altAnim": false,
				"gfSection": false,
				"bpm": 160,
				"changeBPM": false,
				"mustHitSection": true
			},
			{
				"lengthInSteps": 16,
				"typeOfSection": 0,
				"sectionNotes": [
					[
						104000,
						0,
						0
					],
					[
						104166.666666667,
						2,
						0
					],
					[
						104250,
						0,
						0
					],
					[
						104666.666666667,
						1,
						250
					]
				],
				"altAnim": false,
				"gfSection": false,
				"bpm": 160,
				"changeBPM": false,
				"mustHitSection": true
			},
			{
				"lengthInSteps": 16,
				"typeOfSection": 0,
				"sectionNotes": [
					[
						105333.333333333,
						0,
						83.3333333333333
					],
					[
						106000,
						3,
						0
					],
					[
						106166.666666667,
						3,
						0
					],
					[
						106333.333333333,
						1,
						0
					],
					[
						106500,
						1,
						0
					],
					[
						105666.666666667,
						0,
						83.3333333333333
					]
				],
				"altAnim": false,
				"gfSection": false,
				"bpm": 160,
				"changeBPM": false,
				"mustHitSection": true
			},
			{
				"lengthInSteps": 16,
				"typeOfSection": 0,
				"sectionNotes": [
					[
						107666.666666667,
						2,
						0
					],
					[
						107833.333333333,
						2,
						0
					]
				],
				"altAnim": false,
				"gfSection": false,
				"bpm": 160,
				"changeBPM": false,
				"mustHitSection": false
			},
			{
				"lengthInSteps": 16,
				"typeOfSection": 0,
				"sectionNotes": [
					[
						108666.666666667,
						0,
						0
					],
					[
						108833.333333333,
						1,
						0
					],
					[
						109166.666666667,
						3,
						0
					],
					[
						108000,
						3,
						416.666666666667
					]
				],
				"altAnim": false,
				"gfSection": false,
				"bpm": 160,
				"changeBPM": false,
				"mustHitSection": false
			},
			{
				"lengthInSteps": 16,
				"typeOfSection": 0,
				"sectionNotes": [
					[
						110333.333333333,
						2,
						0
					],
					[
						110500,
						3,
						0
					],
					[
						109333.333333333,
						1,
						250
					],
					[
						109666.666666667,
						2,
						250
					],
					[
						110166.666666667,
						0,
						0
					]
				],
				"altAnim": false,
				"gfSection": false,
				"bpm": 160,
				"changeBPM": false,
				"mustHitSection": false
			},
			{
				"lengthInSteps": 16,
				"typeOfSection": 0,
				"sectionNotes": [
					[
						111000,
						3,
						916.666666666667
					],
					[
						110666.666666667,
						1,
						250
					]
				],
				"altAnim": false,
				"gfSection": false,
				"bpm": 160,
				"changeBPM": false,
				"mustHitSection": false
			},
			{
				"lengthInSteps": 16,
				"typeOfSection": 0,
				"sectionNotes": [
					[
						113000,
						1,
						0
					],
					[
						113166.666666667,
						3,
						0
					]
				],
				"altAnim": false,
				"gfSection": false,
				"bpm": 160,
				"changeBPM": false,
				"mustHitSection": true
			},
			{
				"lengthInSteps": 16,
				"typeOfSection": 0,
				"sectionNotes": [
					[
						114166.666666667,
						3,
						0
					],
					[
						114333.333333333,
						2,
						0
					],
					[
						114500,
						3,
						0
					],
					[
						113333.333333333,
						1,
						250
					],
					[
						113666.666666667,
						0,
						333.333333333333
					]
				],
				"altAnim": false,
				"gfSection": false,
				"bpm": 160,
				"changeBPM": false,
				"mustHitSection": true
			},
			{
				"lengthInSteps": 16,
				"typeOfSection": 0,
				"sectionNotes": [
					[
						115000,
						0,
						250
					],
					[
						115333.333333333,
						1,
						250
					],
					[
						115666.666666667,
						3,
						250
					],
					[
						114666.666666667,
						1,
						250
					]
				],
				"altAnim": false,
				"gfSection": false,
				"bpm": 160,
				"changeBPM": false,
				"mustHitSection": true
			},
			{
				"lengthInSteps": 16,
				"typeOfSection": 0,
				"sectionNotes": [
					[
						116000,
						1,
						583.333333333333
					],
					[
						116666.666666667,
						3,
						583.333333333333
					]
				],
				"altAnim": false,
				"gfSection": false,
				"bpm": 160,
				"changeBPM": false,
				"mustHitSection": true
			},
			{
				"lengthInSteps": 16,
				"typeOfSection": 0,
				"sectionNotes": [
					[
						118000,
						2,
						0
					],
					[
						118166.666666667,
						0,
						0
					],
					[
						118333.333333333,
						2,
						0
					],
					[
						118500,
						3,
						0
					]
				],
				"altAnim": false,
				"gfSection": false,
				"bpm": 160,
				"changeBPM": false,
				"mustHitSection": false
			},
			{
				"lengthInSteps": 16,
				"typeOfSection": 0,
				"sectionNotes": [
					[
						118666.666666667,
						0,
						250
					],
					[
						119000,
						3,
						250
					],
					[
						119333.333333333,
						1,
						250
					],
					[
						119666.666666667,
						2,
						250
					]
				],
				"altAnim": false,
				"gfSection": false,
				"bpm": 160,
				"changeBPM": false,
				"mustHitSection": false
			},
			{
				"lengthInSteps": 16,
				"typeOfSection": 0,
				"sectionNotes": [
					[
						120666.666666667,
						3,
						0
					],
					[
						120750,
						2,
						0
					],
					[
						120000,
						1,
						583.333333333333
					],
					[
						121000,
						1,
						250
					],
					[
						120833.333333333,
						3,
						83.3333333333333
					]
				],
				"altAnim": false,
				"gfSection": false,
				"bpm": 160,
				"changeBPM": false,
				"mustHitSection": false
			},
			{
				"lengthInSteps": 16,
				"typeOfSection": 0,
				"sectionNotes": [
					[
						121666.666666667,
						3,
						0
					],
					[
						121833.333333333,
						1,
						0
					],
					[
						122333.333333333,
						1,
						250
					],
					[
						122000,
						2,
						333.333333333333
					],
					[
						121333.333333333,
						2,
						250
					]
				],
				"altAnim": false,
				"gfSection": false,
				"bpm": 160,
				"changeBPM": false,
				"mustHitSection": false
			},
			{
				"lengthInSteps": 16,
				"typeOfSection": 0,
				"sectionNotes": [
					[
						123333.333333333,
						1,
						0
					],
					[
						123500,
						0,
						0
					],
					[
						123666.666666667,
						1,
						0
					],
					[
						123833.333333333,
						3,
						0
					]
				],
				"altAnim": false,
				"gfSection": false,
				"bpm": 160,
				"changeBPM": false,
				"mustHitSection": true
			},
			{
				"lengthInSteps": 16,
				"typeOfSection": 0,
				"sectionNotes": [
					[
						124000,
						2,
						250
					],
					[
						124333.333333333,
						3,
						250
					],
					[
						124666.666666667,
						1,
						250
					],
					[
						125000,
						0,
						250
					]
				],
				"altAnim": false,
				"gfSection": false,
				"bpm": 160,
				"changeBPM": false,
				"mustHitSection": true
			},
			{
				"lengthInSteps": 16,
				"typeOfSection": 0,
				"sectionNotes": [
					[
						126000,
						0,
						0
					],
					[
						126083.333333333,
						2,
						0
					],
					[
						126166.666666667,
						1,
						83.3333333333333
					],
					[
						126333.333333333,
						0,
						250
					],
					[
						125333.333333333,
						2,
						583.333333333333
					]
				],
				"altAnim": false,
				"gfSection": false,
				"bpm": 160,
				"changeBPM": false,
				"mustHitSection": true
			},
			{
				"lengthInSteps": 16,
				"typeOfSection": 0,
				"sectionNotes": [
					[
						127000,
						1,
						0
					],
					[
						127166.666666667,
						3,
						0
					],
					[
						126666.666666667,
						3,
						250
					],
					[
						127333.333333333,
						6,
						583.333333333333
					],
					[
						127333.333333333,
						5,
						583.333333333333,
						"No Animation"
					],
					[
						127333.333333333,
						7,
						583.333333333333,
						"No Animation"
					],
					[
						127333.333333333,
						4,
						583.333333333333,
						"No Animation"
					]
				],
				"altAnim": false,
				"gfSection": false,
				"bpm": 160,
				"changeBPM": false,
				"mustHitSection": true
			},
			{
				"lengthInSteps": 16,
				"typeOfSection": 0,
				"sectionNotes": [
					[
						128166.666666667,
						3,
						0
					],
					[
						128333.333333333,
						1,
						0
					],
					[
						128500,
						2,
						0
					],
					[
						128666.666666667,
						1,
						0
					],
					[
						128833.333333333,
						3,
						0
					],
					[
						129000,
						2,
						0
					],
					[
						129166.666666667,
						3,
						0
					]
				],
				"altAnim": false,
				"gfSection": false,
				"bpm": 160,
				"changeBPM": false,
				"mustHitSection": false
			},
			{
				"lengthInSteps": 16,
				"typeOfSection": 0,
				"sectionNotes": [
					[
						129333.333333333,
						0,
						0
					],
					[
						129500,
						1,
						0
					],
					[
						129666.666666667,
						3,
						0
					],
					[
						129833.333333333,
						2,
						0
					],
					[
						130000,
						1,
						250
					],
					[
						130333.333333333,
						2,
						250
					]
				],
				"altAnim": false,
				"gfSection": false,
				"bpm": 160,
				"changeBPM": false,
				"mustHitSection": false
			},
			{
				"lengthInSteps": 16,
				"typeOfSection": 0,
				"sectionNotes": [
					[
						130666.666666667,
						1,
						0
					],
					[
						130833.333333333,
						2,
						0
					],
					[
						131000,
						1,
						0
					],
					[
						131166.666666667,
						3,
						0
					],
					[
						131333.333333333,
						2,
						0
					],
					[
						131500,
						3,
						0
					],
					[
						131666.666666667,
						1,
						0
					],
					[
						131833.333333333,
						3,
						0
					]
				],
				"altAnim": false,
				"gfSection": false,
				"bpm": 160,
				"changeBPM": false,
				"mustHitSection": false
			},
			{
				"lengthInSteps": 16,
				"typeOfSection": 0,
				"sectionNotes": [
					[
						132000,
						2,
						0
					],
					[
						132166.666666667,
						3,
						0
					],
					[
						132333.333333333,
						1,
						0
					],
					[
						132500,
						3,
						0
					],
					[
						133000,
						0,
						250
					],
					[
						132666.666666667,
						2,
						250
					]
				],
				"altAnim": false,
				"gfSection": false,
				"bpm": 160,
				"changeBPM": false,
				"mustHitSection": false
			},
			{
				"lengthInSteps": 16,
				"typeOfSection": 0,
				"sectionNotes": [
					[
						133500,
						0,
						0
					],
					[
						133666.666666667,
						2,
						0
					],
					[
						133833.333333333,
						1,
						0
					],
					[
						134166.666666667,
						0,
						0
					],
					[
						134000,
						3,
						0
					],
					[
						134333.333333333,
						3,
						0
					],
					[
						134500,
						1,
						0
					]
				],
				"altAnim": false,
				"gfSection": false,
				"bpm": 160,
				"changeBPM": false,
				"mustHitSection": true
			},
			{
				"lengthInSteps": 16,
				"typeOfSection": 0,
				"sectionNotes": [
					[
						134666.666666667,
						3,
						0
					],
					[
						134833.333333333,
						2,
						0
					],
					[
						135166.666666667,
						1,
						0
					],
					[
						135666.666666667,
						1,
						250
					],
					[
						135000,
						3,
						0
					],
					[
						135333.333333333,
						0,
						250
					]
				],
				"altAnim": false,
				"gfSection": false,
				"bpm": 160,
				"changeBPM": false,
				"mustHitSection": true
			},
			{
				"lengthInSteps": 16,
				"typeOfSection": 0,
				"sectionNotes": [
					[
						136000,
						2,
						0
					],
					[
						136166.666666667,
						3,
						0
					],
					[
						136333.333333333,
						1,
						0
					],
					[
						136500,
						0,
						0
					],
					[
						136666.666666667,
						2,
						0
					],
					[
						136833.333333333,
						0,
						0
					],
					[
						137000,
						1,
						0
					],
					[
						137166.666666667,
						2,
						0
					]
				],
				"altAnim": false,
				"gfSection": false,
				"bpm": 160,
				"changeBPM": false,
				"mustHitSection": true
			},
			{
				"lengthInSteps": 16,
				"typeOfSection": 0,
				"sectionNotes": [
					[
						137333.333333333,
						1,
						0
					],
					[
						137416.666666667,
						0,
						0
					],
					[
						137500,
						1,
						0
					],
					[
						137583.333333333,
						3,
						0
					],
					[
						137666.666666667,
						1,
						0
					],
					[
						137833.333333333,
						1,
						0
					],
					[
						138000,
						1,
						0
					],
					[
						138166.666666667,
						0,
						0
					],
					[
						138333.333333333,
						1,
						0
					],
					[
						138500,
						2,
						0
					]
				],
				"altAnim": false,
				"gfSection": false,
				"bpm": 160,
				"changeBPM": false,
				"mustHitSection": true
			},
			{
				"lengthInSteps": 16,
				"typeOfSection": 0,
				"sectionNotes": [
					[
						138666.666666667,
						3,
						0
					],
					[
						138750,
						2,
						0
					],
					[
						138833.333333333,
						3,
						0
					],
					[
						139000,
						2,
						0
					],
					[
						139166.666666667,
						1,
						0
					],
					[
						139375,
						3,
						0
					],
					[
						139416.666666667,
						2,
						0
					],
					[
						139458.333333333,
						0,
						0
					],
					[
						139500,
						1,
						0
					],
					[
						139541.666666667,
						3,
						83.3333333333333
					],
					[
						139666.666666667,
						1,
						0
					],
					[
						139833.333333333,
						2,
						0
					],
					[
						139291.666666667,
						0,
						0
					],
					[
						139333.333333333,
						1,
						0
					]
				],
				"altAnim": false,
				"gfSection": false,
				"bpm": 160,
				"changeBPM": false,
				"mustHitSection": false
			},
			{
				"lengthInSteps": 16,
				"typeOfSection": 0,
				"sectionNotes": [
					[
						140000,
						1,
						0
					],
					[
						140166.666666667,
						3,
						0
					],
					[
						140333.333333333,
						2,
						0
					],
					[
						140500,
						3,
						0
					],
					[
						141000,
						2,
						0
					],
					[
						141083.333333333,
						1,
						0
					],
					[
						141166.666666667,
						2,
						0
					],
					[
						140666.666666667,
						1,
						250
					]
				],
				"altAnim": false,
				"gfSection": false,
				"bpm": 160,
				"changeBPM": false,
				"mustHitSection": false
			},
			{
				"lengthInSteps": 16,
				"typeOfSection": 0,
				"sectionNotes": [
					[
						141333.333333333,
						1,
						0
					],
					[
						141500,
						2,
						0
					],
					[
						141666.666666667,
						1,
						0
					],
					[
						141833.333333333,
						3,
						0
					],
					[
						142000,
						2,
						0
					],
					[
						142166.666666667,
						3,
						0
					],
					[
						142333.333333333,
						1,
						0
					],
					[
						142500,
						3,
						0
					]
				],
				"altAnim": false,
				"gfSection": false,
				"bpm": 160,
				"changeBPM": false,
				"mustHitSection": false
			},
			{
				"lengthInSteps": 16,
				"typeOfSection": 0,
				"sectionNotes": [
					[
						142666.666666667,
						2,
						0
					],
					[
						142833.333333333,
						3,
						0
					],
					[
						143000,
						1,
						0
					],
					[
						143166.666666667,
						3,
						0
					],
					[
						143666.666666667,
						0,
						250
					],
					[
						143333.333333333,
						2,
						250
					]
				],
				"altAnim": false,
				"gfSection": false,
				"bpm": 160,
				"changeBPM": false,
				"mustHitSection": false
			},
			{
				"lengthInSteps": 16,
				"typeOfSection": 0,
				"sectionNotes": [
					[
						144000,
						0,
						0
					],
					[
						144083.333333333,
						1,
						0
					],
					[
						144166.666666667,
						0,
						0
					],
					[
						144333.333333333,
						1,
						0
					],
					[
						144500,
						2,
						0
					],
					[
						144708.333333333,
						0,
						0
					],
					[
						144750,
						1,
						0
					],
					[
						144791.666666667,
						3,
						0
					],
					[
						144833.333333333,
						2,
						0
					],
					[
						144875,
						0,
						83.3333333333333
					],
					[
						145000,
						2,
						0
					],
					[
						145166.666666667,
						1,
						0
					],
					[
						144625,
						3,
						0
					],
					[
						144666.666666667,
						2,
						0
					]
				],
				"altAnim": false,
				"gfSection": false,
				"bpm": 160,
				"changeBPM": false,
				"mustHitSection": true
			},
			{
				"lengthInSteps": 16,
				"typeOfSection": 0,
				"sectionNotes": [
					[
						145333.333333333,
						2,
						0
					],
					[
						145500,
						0,
						0
					],
					[
						145666.666666667,
						1,
						0
					],
					[
						145833.333333333,
						0,
						0
					],
					[
						146333.333333333,
						1,
						0
					],
					[
						146416.666666667,
						2,
						0
					],
					[
						146500,
						1,
						0
					],
					[
						146000,
						2,
						250
					]
				],
				"altAnim": false,
				"gfSection": false,
				"bpm": 160,
				"changeBPM": false,
				"mustHitSection": true
			},
			{
				"lengthInSteps": 16,
				"typeOfSection": 0,
				"sectionNotes": [
					[
						146666.666666667,
						2,
						0
					],
					[
						147166.666666667,
						0,
						0
					],
					[
						147500,
						0,
						0
					],
					[
						147833.333333333,
						0,
						0
					],
					[
						146833.333333333,
						0,
						0
					],
					[
						147000,
						1,
						0
					],
					[
						147333.333333333,
						2,
						0
					],
					[
						147666.666666667,
						2,
						0
					]
				],
				"altAnim": false,
				"gfSection": false,
				"bpm": 160,
				"changeBPM": false,
				"mustHitSection": true
			},
			{
				"lengthInSteps": 16,
				"typeOfSection": 0,
				"sectionNotes": [
					[
						148000,
						2,
						0
					],
					[
						148166.666666667,
						0,
						0
					],
					[
						148333.333333333,
						2,
						0
					],
					[
						148500,
						0,
						0
					],
					[
						148666.666666667,
						2,
						0
					],
					[
						148833.333333333,
						1,
						0
					],
					[
						149000,
						1,
						0
					],
					[
						149250,
						1,
						0
					]
				],
				"altAnim": false,
				"gfSection": false,
				"bpm": 160,
				"changeBPM": false,
				"mustHitSection": true
			},
			{
				"lengthInSteps": 16,
				"typeOfSection": 0,
				"sectionNotes": [
					[
						149500,
						1,
						0
					],
					[
						149666.666666667,
						2,
						0
					],
					[
						149833.333333333,
						1,
						0
					],
					[
						150000,
						3,
						0
					],
					[
						150333.333333333,
						1,
						250
					]
				],
				"altAnim": false,
				"gfSection": false,
				"bpm": 160,
				"changeBPM": false,
				"mustHitSection": false
			},
			{
				"lengthInSteps": 16,
				"typeOfSection": 0,
				"sectionNotes": [
					[
						151166.666666667,
						1,
						0
					],
					[
						151333.333333333,
						2,
						0
					],
					[
						151500,
						1,
						0
					],
					[
						151666.666666667,
						3,
						0
					],
					[
						151833.333333333,
						1,
						0
					]
				],
				"altAnim": false,
				"gfSection": false,
				"bpm": 160,
				"changeBPM": false,
				"mustHitSection": false
			},
			{
				"lengthInSteps": 16,
				"typeOfSection": 0,
				"sectionNotes": [
					[
						152166.666666667,
						1,
						0
					],
					[
						152333.333333333,
						3,
						0
					],
					[
						152500,
						1,
						0
					],
					[
						152666.666666667,
						2,
						0
					],
					[
						153000,
						2,
						0
					]
				],
				"altAnim": false,
				"gfSection": false,
				"bpm": 160,
				"changeBPM": false,
				"mustHitSection": false
			},
			{
				"lengthInSteps": 16,
				"typeOfSection": 0,
				"sectionNotes": [
					[
						153500,
						3,
						0
					],
					[
						153666.666666667,
						2,
						0
					],
					[
						153833.333333333,
						1,
						0
					],
					[
						154000,
						2,
						0
					],
					[
						154166.666666667,
						1,
						0
					],
					[
						154333.333333333,
						2,
						0
					],
					[
						154500,
						3,
						0
					]
				],
				"altAnim": false,
				"gfSection": false,
				"bpm": 160,
				"changeBPM": false,
				"mustHitSection": false
			},
			{
				"lengthInSteps": 16,
				"typeOfSection": 0,
				"sectionNotes": [
					[
						154833.333333333,
						2,
						0
					],
					[
						155000,
						1,
						0
					],
					[
						155166.666666667,
						2,
						0
					],
					[
						155333.333333333,
						0,
						0
					],
					[
						155666.666666667,
						2,
						250
					]
				],
				"altAnim": false,
				"gfSection": false,
				"bpm": 160,
				"changeBPM": false,
				"mustHitSection": true
			},
			{
				"lengthInSteps": 16,
				"typeOfSection": 0,
				"sectionNotes": [
					[
						156666.666666667,
						1,
						0
					],
					[
						157000,
						0,
						0
					],
					[
						156500,
						3,
						0
					],
					[
						156833.333333333,
						3,
						0
					],
					[
						157166.666666667,
						3,
						0
					]
				],
				"altAnim": false,
				"gfSection": false,
				"bpm": 160,
				"changeBPM": false,
				"mustHitSection": true
			},
			{
				"lengthInSteps": 16,
				"typeOfSection": 0,
				"sectionNotes": [
					[
						157666.666666667,
						3,
						0
					],
					[
						157500,
						0,
						0
					],
					[
						157833.333333333,
						0,
						0
					],
					[
						158000,
						3,
						0
					],
					[
						158166.666666667,
						2,
						0
					],
					[
						158333.333333333,
						3,
						0
					],
					[
						158500,
						0,
						0
					]
				],
				"altAnim": false,
				"gfSection": false,
				"bpm": 160,
				"changeBPM": false,
				"mustHitSection": true
			},
			{
				"lengthInSteps": 16,
				"typeOfSection": 0,
				"sectionNotes": [
					[
						158833.333333333,
						3,
						0
					],
					[
						158666.666666667,
						1,
						0
					],
					[
						159000,
						1,
						0
					],
					[
						159166.666666667,
						2,
						0
					],
					[
						159333.333333333,
						0,
						0
					],
					[
						159500,
						2,
						0
					],
					[
						159666.666666667,
						3,
						0
					],
					[
						159833.333333333,
						1,
						0
					]
				],
				"altAnim": false,
				"gfSection": false,
				"bpm": 160,
				"changeBPM": false,
				"mustHitSection": true
			},
			{
				"lengthInSteps": 16,
				"typeOfSection": 0,
				"sectionNotes": [
					[
						160166.666666667,
						5,
						0
					],
					[
						160333.333333333,
						6,
						0
					],
					[
						160500,
						5,
						0
					],
					[
						160666.666666667,
						4,
						750
					],
					[
						160000,
						1,
						0
					],
					[
						160166.666666667,
						1,
						0
					],
					[
						160333.333333333,
						3,
						0
					],
					[
						160500,
						1,
						0
					],
					[
						160666.666666667,
						2,
						0
					],
					[
						161000,
						1,
						0
					],
					[
						161166.666666667,
						3,
						0
					]
				],
				"altAnim": false,
				"gfSection": false,
				"bpm": 160,
				"changeBPM": false,
				"mustHitSection": false
			},
			{
				"lengthInSteps": 16,
				"typeOfSection": 0,
				"sectionNotes": [
					[
						162166.666666667,
						7,
						0
					],
					[
						162333.333333333,
						5,
						250
					],
					[
						161833.333333333,
						5,
						250
					],
					[
						161500,
						7,
						250
					],
					[
						161333.333333333,
						2,
						0
					],
					[
						161500,
						1,
						0
					],
					[
						161666.666666667,
						2,
						0
					],
					[
						161833.333333333,
						1,
						0
					],
					[
						162000,
						3,
						0
					],
					[
						162166.666666667,
						2,
						0
					],
					[
						162333.333333333,
						3,
						0
					],
					[
						162500,
						1,
						0
					]
				],
				"altAnim": false,
				"gfSection": false,
				"bpm": 160,
				"changeBPM": false,
				"mustHitSection": false
			},
			{
				"lengthInSteps": 16,
				"typeOfSection": 0,
				"sectionNotes": [
					[
						163500,
						4,
						416.666666666667
					],
					[
						162666.666666667,
						6,
						666.666666666667
					],
					[
						162666.666666667,
						2,
						0
					],
					[
						162833.333333333,
						3,
						0
					],
					[
						163000,
						2,
						0
					],
					[
						163166.666666667,
						3,
						0
					],
					[
						163333.333333333,
						1,
						0
					],
					[
						163500,
						3,
						0
					],
					[
						163666.666666667,
						1,
						0
					],
					[
						163833.333333333,
						3,
						0
					],
					[
						163916.666666667,
						0,
						0
					]
				],
				"altAnim": false,
				"gfSection": false,
				"bpm": 160,
				"changeBPM": false,
				"mustHitSection": false
			},
			{
				"lengthInSteps": 16,
				"typeOfSection": 0,
				"sectionNotes": [
					[
						164666.666666667,
						4,
						0
					],
					[
						165000,
						5,
						0
					],
					[
						165166.666666667,
						7,
						0
					],
					[
						164000,
						5,
						583.333333333333
					],
					[
						164000,
						1,
						0
					],
					[
						164166.666666667,
						2,
						0
					],
					[
						164333.333333333,
						1,
						0
					],
					[
						164500,
						2,
						0
					],
					[
						164666.666666667,
						0,
						0
					],
					[
						164833.333333333,
						3,
						0
					],
					[
						165000,
						0,
						0
					],
					[
						165166.666666667,
						3,
						0
					]
				],
				"altAnim": false,
				"gfSection": false,
				"bpm": 160,
				"changeBPM": false,
				"mustHitSection": false
			},
			{
				"lengthInSteps": 16,
				"typeOfSection": 0,
				"sectionNotes": [
					[
						165333.333333333,
						1,
						0
					],
					[
						165500,
						3,
						0
					],
					[
						165666.666666667,
						1,
						0
					],
					[
						165833.333333333,
						0,
						0
					],
					[
						166000,
						1,
						0
					],
					[
						166166.666666667,
						0,
						0
					],
					[
						166333.333333333,
						1,
						0
					],
					[
						166500,
						2,
						0
					]
				],
				"altAnim": false,
				"gfSection": false,
				"bpm": 160,
				"changeBPM": false,
				"mustHitSection": true
			},
			{
				"lengthInSteps": 16,
				"typeOfSection": 0,
				"sectionNotes": [
					[
						166833.333333333,
						2,
						0
					],
					[
						167000,
						1,
						0
					],
					[
						167166.666666667,
						2,
						0
					],
					[
						167333.333333333,
						1,
						0
					],
					[
						167500,
						0,
						0
					],
					[
						167666.666666667,
						1,
						0
					],
					[
						167833.333333333,
						0,
						0
					]
				],
				"altAnim": false,
				"gfSection": false,
				"bpm": 160,
				"changeBPM": false,
				"mustHitSection": true
			},
			{
				"lengthInSteps": 16,
				"typeOfSection": 0,
				"sectionNotes": [
					[
						168000,
						1,
						0
					],
					[
						168083.333333333,
						0,
						0
					],
					[
						168166.666666667,
						1,
						0
					],
					[
						168250,
						0,
						0
					],
					[
						168500,
						0,
						0
					],
					[
						168583.333333333,
						2,
						0
					],
					[
						168666.666666667,
						0,
						0
					],
					[
						168750,
						2,
						0
					],
					[
						169083.333333333,
						0,
						166.666666666667
					],
					[
						168833.333333333,
						1,
						166.666666666667
					],
					[
						168333.333333333,
						3,
						83.3333333333333
					]
				],
				"altAnim": false,
				"gfSection": false,
				"bpm": 160,
				"changeBPM": false,
				"mustHitSection": true
			},
			{
				"lengthInSteps": 16,
				"typeOfSection": 0,
				"sectionNotes": [
					[
						169333.333333333,
						1,
						0
					],
					[
						169500,
						1,
						0
					],
					[
						169666.666666667,
						3,
						0
					],
					[
						169833.333333333,
						0,
						0
					],
					[
						170000,
						0,
						0
					],
					[
						170166.666666667,
						1,
						0
					],
					[
						170333.333333333,
						2,
						0
					],
					[
						170500,
						1,
						0
					]
				],
				"altAnim": false,
				"gfSection": false,
				"bpm": 160,
				"changeBPM": false,
				"mustHitSection": true
			},
			{
				"lengthInSteps": 16,
				"typeOfSection": 0,
				"sectionNotes": [
					[
						170833.333333333,
						1,
						0
					],
					[
						171000,
						2,
						0
					],
					[
						171166.666666667,
						1,
						0
					],
					[
						171333.333333333,
						3,
						0
					],
					[
						171666.666666667,
						1,
						0
					]
				],
				"altAnim": false,
				"gfSection": false,
				"bpm": 160,
				"changeBPM": false,
				"mustHitSection": false
			},
			{
				"lengthInSteps": 16,
				"typeOfSection": 0,
				"sectionNotes": [
					[
						172500,
						1,
						0
					],
					[
						172666.666666667,
						3,
						0
					],
					[
						172833.333333334,
						2,
						0
					],
					[
						173000,
						1,
						0
					],
					[
						173166.666666667,
						3,
						0
					]
				],
				"altAnim": false,
				"gfSection": false,
				"bpm": 160,
				"changeBPM": false,
				"mustHitSection": false
			},
			{
				"lengthInSteps": 16,
				"typeOfSection": 0,
				"sectionNotes": [
					[
						173333.333333334,
						1,
						0
					],
					[
						173500,
						1,
						0
					],
					[
						173666.666666667,
						2,
						0
					],
					[
						173833.333333334,
						3,
						0
					],
					[
						174000,
						2,
						0
					],
					[
						174166.666666667,
						0,
						0
					],
					[
						174333.333333334,
						1,
						0
					],
					[
						174500,
						3,
						0
					]
				],
				"altAnim": false,
				"gfSection": false,
				"bpm": 160,
				"changeBPM": false,
				"mustHitSection": false
			},
			{
				"lengthInSteps": 16,
				"typeOfSection": 0,
				"sectionNotes": [
					[
						174666.666666667,
						1,
						0
					],
					[
						174833.333333334,
						0,
						0
					],
					[
						174916.666666667,
						2,
						0
					],
					[
						175166.666666667,
						1,
						0
					],
					[
						175250,
						3,
						0
					],
					[
						175333.333333334,
						1,
						0
					],
					[
						175416.666666667,
						2,
						0
					],
					[
						175500,
						3,
						0
					],
					[
						175583.333333334,
						2,
						0
					],
					[
						175666.666666667,
						3,
						0
					],
					[
						175750,
						1,
						0
					],
					[
						175833.333333334,
						2,
						0
					],
					[
						175916.666666667,
						1,
						0
					]
				],
				"altAnim": false,
				"gfSection": false,
				"bpm": 160,
				"changeBPM": false,
				"mustHitSection": false
			},
			{
				"lengthInSteps": 16,
				"typeOfSection": 0,
				"sectionNotes": [
					[
						176166.666666667,
						1,
						0
					],
					[
						176500,
						1,
						0
					],
					[
						177000,
						1,
						250
					],
					[
						176333.333333334,
						0,
						0
					],
					[
						176666.666666667,
						2,
						166.666666666667
					]
				],
				"altAnim": false,
				"gfSection": false,
				"bpm": 160,
				"changeBPM": false,
				"mustHitSection": true
			},
			{
				"lengthInSteps": 16,
				"typeOfSection": 0,
				"sectionNotes": [
					[
						178166.666666667,
						1,
						0
					],
					[
						178333.333333334,
						2,
						0
					],
					[
						178500,
						1,
						0
					],
					[
						177833.333333334,
						0,
						0
					],
					[
						178000,
						2,
						0
					]
				],
				"altAnim": false,
				"gfSection": false,
				"bpm": 160,
				"changeBPM": false,
				"mustHitSection": true
			},
			{
				"lengthInSteps": 16,
				"typeOfSection": 0,
				"sectionNotes": [
					[
						178666.666666667,
						2,
						0
					],
					[
						178833.333333334,
						2,
						0
					],
					[
						179000,
						1,
						0
					],
					[
						179166.666666667,
						0,
						0
					],
					[
						179333.333333334,
						1,
						0
					],
					[
						179500,
						3,
						0
					],
					[
						179666.666666667,
						2,
						0
					],
					[
						179833.333333334,
						0,
						0
					],
					[
						179083.333333334,
						2,
						0
					]
				],
				"altAnim": false,
				"gfSection": false,
				"bpm": 160,
				"changeBPM": false,
				"mustHitSection": true
			},
			{
				"lengthInSteps": 16,
				"typeOfSection": 0,
				"sectionNotes": [
					[
						180333.333333334,
						0,
						250
					],
					[
						180666.666666667,
						1,
						250
					],
					[
						181000,
						3,
						250
					],
					[
						180000,
						2,
						250
					]
				],
				"altAnim": false,
				"gfSection": false,
				"bpm": 160,
				"changeBPM": false,
				"mustHitSection": true
			},
			{
				"lengthInSteps": 16,
				"typeOfSection": 0,
				"sectionNotes": [
					[
						181333.333333334,
						1,
						0
					],
					[
						181500,
						1,
						0
					],
					[
						181666.666666667,
						3,
						0
					],
					[
						181833.333333334,
						1,
						0
					],
					[
						182000,
						1,
						0
					],
					[
						182166.666666667,
						3,
						0
					],
					[
						182333.333333334,
						0,
						0
					],
					[
						182500,
						2,
						0
					]
				],
				"altAnim": false,
				"gfSection": false,
				"bpm": 160,
				"changeBPM": false,
				"mustHitSection": false
			},
			{
				"lengthInSteps": 16,
				"typeOfSection": 0,
				"sectionNotes": [
					[
						182666.666666667,
						3,
						0
					],
					[
						182833.333333334,
						3,
						0
					],
					[
						183000,
						0,
						0
					],
					[
						183166.666666667,
						3,
						0
					],
					[
						183333.333333334,
						3,
						0
					],
					[
						183500,
						0,
						0
					],
					[
						183666.666666667,
						1,
						0
					],
					[
						183833.333333334,
						3,
						0
					]
				],
				"altAnim": false,
				"gfSection": false,
				"bpm": 160,
				"changeBPM": false,
				"mustHitSection": true
			},
			{
				"lengthInSteps": 16,
				"typeOfSection": 0,
				"sectionNotes": [
					[
						184000,
						2,
						0
					],
					[
						184166.666666667,
						2,
						0
					],
					[
						184333.333333334,
						2,
						0
					],
					[
						184416.666666667,
						3,
						0
					],
					[
						184500,
						2,
						0
					],
					[
						184583.333333334,
						3,
						0
					],
					[
						184666.666666667,
						2,
						0
					],
					[
						185000,
						3,
						0
					],
					[
						185166.666666667,
						2,
						0
					],
					[
						184833.333333334,
						0,
						0
					]
				],
				"altAnim": false,
				"gfSection": false,
				"bpm": 160,
				"changeBPM": false,
				"mustHitSection": false
			},
			{
				"lengthInSteps": 16,
				"typeOfSection": 0,
				"sectionNotes": [
					[
						185333.333333334,
						2,
						0
					],
					[
						185500,
						2,
						0
					],
					[
						185666.666666667,
						2,
						0
					],
					[
						185750,
						0,
						0
					],
					[
						185833.333333334,
						2,
						0
					],
					[
						185916.666666667,
						0,
						0
					],
					[
						186000,
						3,
						83.3333333333333
					],
					[
						186166.666666667,
						2,
						83.3333333333333
					],
					[
						186333.333333334,
						0,
						83.3333333333333
					],
					[
						186500,
						2,
						83.3333333333333
					]
				],
				"altAnim": false,
				"gfSection": false,
				"bpm": 160,
				"changeBPM": false,
				"mustHitSection": true
			},
			{
				"lengthInSteps": 16,
				"typeOfSection": 0,
				"sectionNotes": [
					[
						186666.666666667,
						1,
						0
					],
					[
						186833.333333334,
						3,
						0
					],
					[
						187000,
						4,
						0
					],
					[
						187166.666666667,
						5,
						0
					],
					[
						187333.333333334,
						3,
						0
					],
					[
						187416.666666667,
						1,
						0
					],
					[
						187500,
						3,
						0
					],
					[
						187583.333333334,
						1,
						0
					],
					[
						187666.666666667,
						2,
						0
					],
					[
						187833.333333334,
						7,
						0
					]
				],
				"altAnim": false,
				"gfSection": false,
				"bpm": 160,
				"changeBPM": false,
				"mustHitSection": false
			},
			{
				"lengthInSteps": 16,
				"typeOfSection": 0,
				"sectionNotes": [
					[
						188000,
						0,
						0
					],
					[
						188166.666666667,
						3,
						0
					],
					[
						188333.333333334,
						0,
						0
					],
					[
						188500,
						3,
						0
					],
					[
						188666.666666667,
						0,
						0
					],
					[
						188833.333333334,
						1,
						0
					],
					[
						189000,
						0,
						0
					],
					[
						189166.666666667,
						2,
						0
					]
				],
				"altAnim": false,
				"gfSection": false,
				"bpm": 160,
				"changeBPM": false,
				"mustHitSection": true
			},
			{
				"lengthInSteps": 16,
				"typeOfSection": 0,
				"sectionNotes": [
					[
						189333.333333334,
						3,
						0
					],
					[
						189416.666666667,
						1,
						0
					],
					[
						189500,
						2,
						0
					],
					[
						189583.333333334,
						1,
						0
					],
					[
						189666.666666667,
						3,
						0
					],
					[
						189750,
						1,
						0
					],
					[
						189833.333333334,
						2,
						0
					],
					[
						189916.666666667,
						3,
						0
					],
					[
						190000,
						1,
						0
					],
					[
						190083.333333334,
						0,
						0
					],
					[
						190166.666666667,
						2,
						0
					],
					[
						190250,
						3,
						0
					],
					[
						190333.333333334,
						2,
						0
					],
					[
						190416.666666667,
						1,
						0
					],
					[
						190500,
						2,
						0
					],
					[
						190583.333333334,
						0,
						0
					]
				],
				"altAnim": false,
				"gfSection": false,
				"bpm": 160,
				"changeBPM": false,
				"mustHitSection": false
			},
			{
				"lengthInSteps": 16,
				"typeOfSection": 0,
				"sectionNotes": [
					[
						191250,
						5,
						666.666666666667
					],
					[
						190666.666666667,
						6,
						500
					],
					[
						190666.666666667,
						3,
						0
					],
					[
						190750,
						1,
						0
					],
					[
						190833.333333334,
						2,
						0
					],
					[
						190916.666666667,
						1,
						0
					],
					[
						191000,
						3,
						0
					],
					[
						191083.333333334,
						1,
						0
					],
					[
						191166.666666667,
						2,
						0
					],
					[
						191250,
						3,
						0
					],
					[
						191333.333333334,
						1,
						0
					],
					[
						191416.666666667,
						0,
						0
					],
					[
						191500,
						2,
						0
					],
					[
						191583.333333334,
						3,
						0
					],
					[
						191666.666666667,
						2,
						0
					],
					[
						191750,
						1,
						0
					],
					[
						191833.333333334,
						2,
						0
					],
					[
						191916.666666667,
						0,
						0
					]
				],
				"altAnim": false,
				"gfSection": false,
				"bpm": 160,
				"changeBPM": false,
				"mustHitSection": true
			},
			{
				"lengthInSteps": 16,
				"typeOfSection": 0,
				"sectionNotes": [
					[
						192000,
						1,
						1250
					],
					[
						192000,
						4,
						1333.33333333333
					],
					[
						192000,
						6,
						1333.33333333333
					]
				],
				"altAnim": false,
				"gfSection": false,
				"bpm": 160,
				"changeBPM": false,
				"mustHitSection": true
			},
			{
				"lengthInSteps": 16,
				"typeOfSection": 0,
				"sectionNotes": [],
				"altAnim": false,
				"gfSection": false,
				"bpm": 160,
				"changeBPM": false,
				"mustHitSection": true
			},
			{
				"lengthInSteps": 16,
				"typeOfSection": 0,
				"sectionNotes": [],
				"altAnim": false,
				"gfSection": false,
				"bpm": 160,
				"changeBPM": false,
				"mustHitSection": true
			},
			{
				"lengthInSteps": 16,
				"typeOfSection": 0,
				"sectionNotes": [],
				"altAnim": false,
				"gfSection": false,
				"bpm": 160,
				"changeBPM": false,
				"mustHitSection": true
			},
			{
				"sectionNotes": [],
				"typeOfSection": 0,
				"lengthInSteps": 16,
				"gfSection": false,
				"altAnim": false,
				"mustHitSection": true,
				"changeBPM": false,
				"bpm": 160
			},
			{
				"sectionNotes": [],
				"typeOfSection": 0,
				"lengthInSteps": 16,
				"gfSection": false,
				"altAnim": false,
				"mustHitSection": true,
				"changeBPM": false,
				"bpm": 160
			},
			{
				"sectionNotes": [],
				"typeOfSection": 0,
				"lengthInSteps": 16,
				"gfSection": false,
				"altAnim": false,
				"mustHitSection": true,
				"changeBPM": false,
				"bpm": 160
			},
			{
				"sectionNotes": [],
				"typeOfSection": 0,
				"lengthInSteps": 16,
				"gfSection": false,
				"altAnim": false,
				"mustHitSection": true,
				"changeBPM": false,
				"bpm": 160
			},
			{
				"sectionNotes": [],
				"typeOfSection": 0,
				"lengthInSteps": 16,
				"gfSection": false,
				"altAnim": false,
				"mustHitSection": true,
				"changeBPM": false,
				"bpm": 160
			},
			{
				"sectionNotes": [],
				"typeOfSection": 0,
				"lengthInSteps": 16,
				"gfSection": false,
				"altAnim": false,
				"mustHitSection": true,
				"changeBPM": false,
				"bpm": 160
			},
			{
				"sectionNotes": [],
				"typeOfSection": 0,
				"lengthInSteps": 16,
				"gfSection": false,
				"altAnim": false,
				"mustHitSection": true,
				"changeBPM": false,
				"bpm": 160
			},
			{
				"sectionNotes": [],
				"typeOfSection": 0,
				"lengthInSteps": 16,
				"gfSection": false,
				"altAnim": false,
				"mustHitSection": true,
				"changeBPM": false,
				"bpm": 160
			},
			{
				"sectionNotes": [],
				"typeOfSection": 0,
				"lengthInSteps": 16,
				"gfSection": false,
				"altAnim": false,
				"mustHitSection": true,
				"changeBPM": false,
				"bpm": 160
			},
			{
				"sectionNotes": [],
				"typeOfSection": 0,
				"lengthInSteps": 16,
				"gfSection": false,
				"altAnim": false,
				"mustHitSection": true,
				"changeBPM": false,
				"bpm": 160
			},
			{
				"lengthInSteps": 16,
				"typeOfSection": 0,
				"sectionNotes": [],
				"altAnim": false,
				"gfSection": false,
				"bpm": 160,
				"changeBPM": false,
				"mustHitSection": true
			},
			{
				"sectionNotes": [],
				"typeOfSection": 0,
				"lengthInSteps": 16,
				"gfSection": false,
				"altAnim": false,
				"mustHitSection": true,
				"changeBPM": false,
				"bpm": 160
			},
			{
				"lengthInSteps": 16,
				"typeOfSection": 0,
				"sectionNotes": [],
				"altAnim": false,
				"gfSection": false,
				"bpm": 160,
				"changeBPM": false,
				"mustHitSection": true
			},
			{
				"lengthInSteps": 16,
				"typeOfSection": 0,
				"sectionNotes": [],
				"altAnim": false,
				"gfSection": false,
				"bpm": 160,
				"changeBPM": false,
				"mustHitSection": true
			},
			{
				"sectionBeats": 4,
				"sectionNotes": [],
				"typeOfSection": 0,
				"gfSection": false,
				"altAnim": false,
				"mustHitSection": true,
				"changeBPM": false,
				"bpm": 160
			},
			{
				"gfSection": false,
				"altAnim": false,
				"typeOfSection": 0,
				"sectionNotes": [],
				"bpm": 160,
				"sectionBeats": 4,
				"changeBPM": false,
				"mustHitSection": true
			},
			{
				"gfSection": false,
				"altAnim": false,
				"typeOfSection": 0,
				"sectionNotes": [],
				"bpm": 160,
				"sectionBeats": 4,
				"changeBPM": false,
				"mustHitSection": true
			}
		],
		"events": [],
		"player2": "nyanyo",
		"player3": null,
		"splashSkin": "noteSplashes",
		"song": "kyatto",
		"needsVoices": true,
		"arrowSkin": "",
		"validScore": true,
		"stage": "kyatto",
		"bpm": 160,
		"speed": 2.5
	}
}